hpc_task/__init__.py
hpc_task/hpc.py
hpc_task-0.1.1.dist-info/licenses/LICENSE
hpc_task-0.1.1.dist-info/METADATA
hpc_task-0.1.1.dist-info/WHEEL
hpc_task-0.1.1.dist-info/top_level.txt
hpc_task-0.1.1.dist-info/RECORD
