Metadata-Version: 2.4
Name: hpc_task
Version: 0.1.1
Summary: HPC Task python library.
Home-page: https://gitee.com/pjren/hpc_task
Author: Renpj
Author-email: 0403114076@163.com
License: MIT
Classifier: Programming Language :: Python :: 3
Classifier: Operating System :: OS Independent
License-File: LICENSE
Requires-Dist: ase
Requires-Dist: paramiko
Dynamic: author
Dynamic: author-email
Dynamic: classifier
Dynamic: description
Dynamic: description-content-type
Dynamic: home-page
Dynamic: license
Dynamic: license-file
Dynamic: requires-dist
Dynamic: summary
